[
 {
  "qualification_id": "Q:A-1",
  "parent_qualification_id": null,
  "manual_type": "both",
  "group": "A",
  "code": "A-1",
  "name_ko": "외교",
  "activity_scope": "",
  "eligible_persons": "",
  "stay_limit": "재임기간",
  "delegated_to": null,
  "program_ids": [],
  "sub_codes": [],
  "confidence": "high",
  "notes": "",
  "status": "active"
 },
 {
  "qualification_id": "Q:A-2",
  "parent_qualification_id": null,
  "manual_type": "both",
  "group": "A",
  "code": "A-2",
  "name_ko": "공무",
  "activity_scope": "",
  "eligible_persons": "",
  "stay_limit": "공무수행기간",
  "delegated_to": null,
  "program_ids": [],
  "sub_codes": [],
  "confidence": "high",
  "notes": "",
  "status": "active"
 },
 {
  "qualification_id": "Q:A-3",
  "parent_qualification_id": null,
  "manual_type": "both",
  "group": "A",
  "code": "A-3",
  "name_ko": "협정",
  "activity_scope": "",
  "eligible_persons": "",
  "stay_limit": "신분존속기간 또는 협정상의 체류기간",
  "delegated_to": null,
  "program_ids": [],
  "sub_codes": [],
  "confidence": "high",
  "notes": "",
  "status": "active"
 },
 {
  "qualification_id": "Q:B-1",
  "parent_qualification_id": null,
  "manual_type": "both",
  "group": "B",
  "code": "B-1",
  "name_ko": "사증면제",
  "activity_scope": "",
  "eligible_persons": "",
  "stay_limit": "협정상의 체류기간",
  "delegated_to": null,
  "program_ids": [],
  "sub_codes": [],
  "confidence": "high",
  "notes": "",
  "status": "active"
 },
 {
  "qualification_id": "Q:B-2",
  "parent_qualification_id": null,
  "manual_type": "both",
  "group": "B",
  "code": "B-2",
  "name_ko": "관광·통과",
  "activity_scope": "",
  "eligible_persons": "",
  "stay_limit": "협정상의 체류기간",
  "delegated_to": null,
  "program_ids": [],
  "sub_codes": [],
  "confidence": "high",
  "notes": "",
  "status": "active"
 },
 {
  "qualification_id": "Q:C-1",
  "parent_qualification_id": null,
  "manual_type": "both",
  "group": "C",
  "code": "C-1",
  "name_ko": "일시취재",
  "activity_scope": "",
  "eligible_persons": "",
  "stay_limit": "90일",
  "delegated_to": null,
  "program_ids": [],
  "sub_codes": [],
  "confidence": "high",
  "notes": "",
  "status": "active"
 },
 {
  "qualification_id": "Q:C-3",
  "parent_qualification_id": null,
  "manual_type": "both",
  "group": "C",
  "code": "C-3",
  "name_ko": "단기방문",
  "activity_scope": "",
  "eligible_persons": "",
  "stay_limit": "90일",
  "delegated_to": null,
  "program_ids": [],
  "sub_codes": [
   "C-3-8"
  ],
  "confidence": "high",
  "notes": "",
  "status": "active"
 },
 {
  "qualification_id": "Q:C-4",
  "parent_qualification_id": null,
  "manual_type": "both",
  "group": "C",
  "code": "C-4",
  "name_ko": "단기취업",
  "activity_scope": "",
  "eligible_persons": "",
  "stay_limit": "90일",
  "delegated_to": null,
  "program_ids": [],
  "sub_codes": [],
  "confidence": "high",
  "notes": "",
  "status": "active"
 },
 {
  "qualification_id": "Q:D-1",
  "parent_qualification_id": null,
  "manual_type": "both",
  "group": "D",
  "code": "D-1",
  "name_ko": "문화예술",
  "activity_scope": "",
  "eligible_persons": "",
  "stay_limit": "2년",
  "delegated_to": null,
  "program_ids": [],
  "sub_codes": [],
  "confidence": "high",
  "notes": "",
  "status": "active"
 },
 {
  "qualification_id": "Q:D-2",
  "parent_qualification_id": null,
  "manual_type": "both",
  "group": "D",
  "code": "D-2",
  "name_ko": "유학",
  "activity_scope": "",
  "eligible_persons": "",
  "stay_limit": "2년",
  "delegated_to": null,
  "program_ids": [],
  "sub_codes": [
   "D-2-1",
   "D-2-2",
   "D-2-3",
   "D-2-4",
   "D-2-5",
   "D-2-6",
   "D-2-7",
   "D-2-8"
  ],
  "confidence": "high",
  "notes": "",
  "status": "active"
 },
 {
  "qualification_id": "Q:D-3",
  "parent_qualification_id": null,
  "manual_type": "both",
  "group": "D",
  "code": "D-3",
  "name_ko": "기술연수",
  "activity_scope": "",
  "eligible_persons": "",
  "stay_limit": "2년",
  "delegated_to": null,
  "program_ids": [],
  "sub_codes": [],
  "confidence": "high",
  "notes": "",
  "status": "active"
 },
 {
  "qualification_id": "Q:D-4",
  "parent_qualification_id": null,
  "manual_type": "both",
  "group": "D",
  "code": "D-4",
  "name_ko": "일반연수",
  "activity_scope": "",
  "eligible_persons": "",
  "stay_limit": "2년",
  "delegated_to": null,
  "program_ids": [],
  "sub_codes": [
   "D-4-1",
   "D-4-2",
   "D-4-5",
   "D-4-7",
   "D-4-2K"
  ],
  "confidence": "high",
  "notes": "",
  "status": "active"
 },
 {
  "qualification_id": "Q:D-5",
  "parent_qualification_id": null,
  "manual_type": "both",
  "group": "D",
  "code": "D-5",
  "name_ko": "취재",
  "activity_scope": "",
  "eligible_persons": "",
  "stay_limit": "2년",
  "delegated_to": null,
  "program_ids": [],
  "sub_codes": [],
  "confidence": "high",
  "notes": "",
  "status": "active"
 },
 {
  "qualification_id": "Q:D-6",
  "parent_qualification_id": null,
  "manual_type": "both",
  "group": "D",
  "code": "D-6",
  "name_ko": "종교",
  "activity_scope": "",
  "eligible_persons": "",
  "stay_limit": "2년",
  "delegated_to": null,
  "program_ids": [],
  "sub_codes": [],
  "confidence": "high",
  "notes": "",
  "status": "active"
 },
 {
  "qualification_id": "Q:D-7",
  "parent_qualification_id": null,
  "manual_type": "both",
  "group": "D",
  "code": "D-7",
  "name_ko": "주재",
  "activity_scope": "",
  "eligible_persons": "",
  "stay_limit": "3년",
  "delegated_to": null,
  "program_ids": [],
  "sub_codes": [],
  "confidence": "high",
  "notes": "",
  "status": "active"
 },
 {
  "qualification_id": "Q:D-8",
  "parent_qualification_id": null,
  "manual_type": "both",
  "group": "D",
  "code": "D-8",
  "name_ko": "기업투자",
  "activity_scope": "",
  "eligible_persons": "",
  "stay_limit": "주재활동 5년 · 벤처기업 설립자 2년(예비 벤처기업 6개월)",
  "delegated_to": null,
  "program_ids": [],
  "sub_codes": [
   "D-8-1",
   "D-8-2",
   "D-8-3",
   "D-8-4",
   "D-8-4S"
  ],
  "confidence": "high",
  "notes": "",
  "status": "active"
 },
 {
  "qualification_id": "Q:D-9",
  "parent_qualification_id": null,
  "manual_type": "both",
  "group": "D",
  "code": "D-9",
  "name_ko": "무역경영",
  "activity_scope": "",
  "eligible_persons": "",
  "stay_limit": "2년",
  "delegated_to": null,
  "program_ids": [],
  "sub_codes": [
   "D-9-1",
   "D-9-4"
  ],
  "confidence": "high",
  "notes": "",
  "status": "active"
 },
 {
  "qualification_id": "Q:D-10",
  "parent_qualification_id": null,
  "manual_type": "both",
  "group": "D",
  "code": "D-10",
  "name_ko": "구직",
  "activity_scope": "",
  "eligible_persons": "",
  "stay_limit": "1년",
  "delegated_to": null,
  "program_ids": [],
  "sub_codes": [
   "D-10-1",
   "D-10-2",
   "D-10-3",
   "D-10-T"
  ],
  "confidence": "high",
  "notes": "",
  "status": "active"
 },
 {
  "qualification_id": "Q:E-1",
  "parent_qualification_id": null,
  "manual_type": "both",
  "group": "E",
  "code": "E-1",
  "name_ko": "교수",
  "activity_scope": "",
  "eligible_persons": "",
  "stay_limit": "5년",
  "delegated_to": null,
  "program_ids": [],
  "sub_codes": [],
  "confidence": "high",
  "notes": "",
  "status": "active"
 },
 {
  "qualification_id": "Q:E-2",
  "parent_qualification_id": null,
  "manual_type": "both",
  "group": "E",
  "code": "E-2",
  "name_ko": "회화지도",
  "activity_scope": "",
  "eligible_persons": "",
  "stay_limit": "2년",
  "delegated_to": null,
  "program_ids": [],
  "sub_codes": [],
  "confidence": "high",
  "notes": "",
  "status": "active"
 },
 {
  "qualification_id": "Q:E-3",
  "parent_qualification_id": null,
  "manual_type": "both",
  "group": "E",
  "code": "E-3",
  "name_ko": "연구",
  "activity_scope": "",
  "eligible_persons": "",
  "stay_limit": "5년",
  "delegated_to": null,
  "program_ids": [],
  "sub_codes": [],
  "confidence": "high",
  "notes": "",
  "status": "active"
 },
 {
  "qualification_id": "Q:E-4",
  "parent_qualification_id": null,
  "manual_type": "both",
  "group": "E",
  "code": "E-4",
  "name_ko": "기술지도",
  "activity_scope": "",
  "eligible_persons": "",
  "stay_limit": "5년",
  "delegated_to": null,
  "program_ids": [],
  "sub_codes": [],
  "confidence": "high",
  "notes": "",
  "status": "active"
 },
 {
  "qualification_id": "Q:E-5",
  "parent_qualification_id": null,
  "manual_type": "both",
  "group": "E",
  "code": "E-5",
  "name_ko": "전문직업",
  "activity_scope": "",
  "eligible_persons": "",
  "stay_limit": "5년",
  "delegated_to": null,
  "program_ids": [],
  "sub_codes": [],
  "confidence": "high",
  "notes": "",
  "status": "active"
 },
 {
  "qualification_id": "Q:E-6",
  "parent_qualification_id": null,
  "manual_type": "both",
  "group": "E",
  "code": "E-6",
  "name_ko": "예술흥행",
  "activity_scope": "",
  "eligible_persons": "",
  "stay_limit": "2년",
  "delegated_to": null,
  "program_ids": [],
  "sub_codes": [],
  "confidence": "high",
  "notes": "",
  "status": "active"
 },
 {
  "qualification_id": "Q:E-7",
  "parent_qualification_id": null,
  "manual_type": "both",
  "group": "E",
  "code": "E-7",
  "name_ko": "특정활동",
  "activity_scope": "",
  "eligible_persons": "",
  "stay_limit": "3년",
  "delegated_to": null,
  "program_ids": [],
  "sub_codes": [
   "E-7-1",
   "E-7-2",
   "E-7-3",
   "E-7-4",
   "E-7-4R",
   "E-7-T",
   "E-7-Y",
   "E-7-S1",
   "E-7-S2"
  ],
  "confidence": "high",
  "notes": "도입방법 원칙(확정): 사증발급인정 신청 원칙, 예외로 E-7-4만 변경허가 경로.",
  "status": "active"
 },
 {
  "qualification_id": "Q:E-8",
  "parent_qualification_id": null,
  "manual_type": "both",
  "group": "E",
  "code": "E-8",
  "name_ko": "계절근로",
  "activity_scope": "",
  "eligible_persons": "계절근로 성인(고용주 매칭·지자체 관리)",
  "stay_limit": "8개월(총 체류기간 8개월 초과 불가)",
  "delegated_to": null,
  "program_ids": [],
  "sub_codes": [],
  "confidence": "high",
  "notes": "체류 챕터 2쪽 축약은 실제 구조(확정). 사증은 인정서 전용.",
  "status": "active"
 },
 {
  "qualification_id": "Q:E-9",
  "parent_qualification_id": null,
  "manual_type": "both",
  "group": "E",
  "code": "E-9",
  "name_ko": "비전문취업",
  "activity_scope": "",
  "eligible_persons": "",
  "stay_limit": "3년",
  "delegated_to": null,
  "program_ids": [],
  "sub_codes": [
   "E-9-1",
   "E-9-2",
   "E-9-3",
   "E-9-4",
   "E-9-5"
  ],
  "confidence": "high",
  "notes": "",
  "status": "active"
 },
 {
  "qualification_id": "Q:E-10",
  "parent_qualification_id": null,
  "manual_type": "both",
  "group": "E",
  "code": "E-10",
  "name_ko": "선원취업",
  "activity_scope": "",
  "eligible_persons": "",
  "stay_limit": "3년",
  "delegated_to": null,
  "program_ids": [],
  "sub_codes": [
   "E-10-2"
  ],
  "confidence": "high",
  "notes": "",
  "status": "active"
 },
 {
  "qualification_id": "Q:F-1",
  "parent_qualification_id": null,
  "manual_type": "both",
  "group": "F",
  "code": "F-1",
  "name_ko": "방문동거",
  "activity_scope": "",
  "eligible_persons": "",
  "stay_limit": "2년",
  "delegated_to": null,
  "program_ids": [],
  "sub_codes": [
   "F-1-11",
   "F-1-12",
   "F-1-13",
   "F-1-15",
   "F-1-16",
   "F-1-21",
   "F-1-22",
   "F-1-23",
   "F-1-24",
   "F-1-28",
   "F-1-4",
   "F-1-5",
   "F-1-51",
   "F-1-52",
   "F-1-6",
   "F-1-9",
   "F-1-D"
  ],
  "confidence": "high",
  "notes": "",
  "status": "active"
 },
 {
  "qualification_id": "Q:F-2",
  "parent_qualification_id": null,
  "manual_type": "both",
  "group": "F",
  "code": "F-2",
  "name_ko": "거주",
  "activity_scope": "영주자격을 부여받기 위하여 국내 장기체류하려는 자",
  "eligible_persons": "가. 국민의 미성년 외국인 자녀 또는 별표1의3 영주(F-5) 소지자의 배우자 및 그의 미성년 자녀 / 나. 국민과 혼인관계(사실상의 혼인관계 포함) …",
  "stay_limit": "5년",
  "delegated_to": null,
  "program_ids": [],
  "sub_codes": [
   "F-2-3",
   "F-2-4",
   "F-2-5",
   "F-2-6",
   "F-2-7",
   "F-2-7S",
   "F-2-71",
   "F-2-99",
   "F-2-R",
   "F-2-T",
   "F-2-T1"
  ],
  "confidence": "high",
  "notes": "섹션 경계 매뉴얼 기준 확인.",
  "status": "active"
 },
 {
  "qualification_id": "Q:F-3",
  "parent_qualification_id": null,
  "manual_type": "both",
  "group": "F",
  "code": "F-3",
  "name_ko": "동반",
  "activity_scope": "",
  "eligible_persons": "",
  "stay_limit": "동반 대상 본인의 체류자격별 상한에 따름",
  "delegated_to": null,
  "program_ids": [],
  "sub_codes": [
   "F-3-18",
   "F-3-19",
   "F-3-1R",
   "F-3-20",
   "F-3-2R",
   "F-3-3R",
   "F-3-17",
   "F-3-10"
  ],
  "confidence": "high",
  "notes": "",
  "status": "active"
 },
 {
  "qualification_id": "Q:F-4",
  "parent_qualification_id": null,
  "manual_type": "both",
  "group": "F",
  "code": "F-4",
  "name_ko": "재외동포",
  "activity_scope": "",
  "eligible_persons": "",
  "stay_limit": "3년",
  "delegated_to": "PG:DONGPO",
  "program_ids": [
   "PG:DONGPO"
  ],
  "sub_codes": [
   "F-4-19",
   "F-4-R"
  ],
  "confidence": "high",
  "notes": "사증 본편 챕터 없음('※ 38.번참조') — 동포매뉴얼 위임.",
  "status": "active"
 },
 {
  "qualification_id": "Q:F-5",
  "parent_qualification_id": null,
  "manual_type": "both",
  "group": "F",
  "code": "F-5",
  "name_ko": "영주",
  "activity_scope": "",
  "eligible_persons": "",
  "stay_limit": "상한 없음",
  "delegated_to": null,
  "program_ids": [],
  "sub_codes": [
   "F-5-1",
   "F-5-2",
   "F-5-6",
   "F-5-10",
   "F-5-11",
   "F-5-14",
   "F-5-S1",
   "F-5-S2",
   "F-5-T",
   "F-5-T1",
   "F-5-6R"
  ],
  "confidence": "high",
  "notes": "",
  "status": "active"
 },
 {
  "qualification_id": "Q:F-6",
  "parent_qualification_id": null,
  "manual_type": "both",
  "group": "F",
  "code": "F-6",
  "name_ko": "결혼이민",
  "activity_scope": "",
  "eligible_persons": "",
  "stay_limit": "3년",
  "delegated_to": null,
  "program_ids": [],
  "sub_codes": [
   "F-6-1",
   "F-6-2",
   "F-6-3"
  ],
  "confidence": "high",
  "notes": "",
  "status": "active"
 },
 {
  "qualification_id": "Q:G-1",
  "parent_qualification_id": null,
  "manual_type": "both",
  "group": "G",
  "code": "G-1",
  "name_ko": "기타",
  "activity_scope": "",
  "eligible_persons": "",
  "stay_limit": "1년",
  "delegated_to": null,
  "program_ids": [],
  "sub_codes": [
   "G-1-10"
  ],
  "confidence": "high",
  "notes": "",
  "status": "active"
 },
 {
  "qualification_id": "Q:H-1",
  "parent_qualification_id": null,
  "manual_type": "both",
  "group": "H",
  "code": "H-1",
  "name_ko": "관광취업",
  "activity_scope": "",
  "eligible_persons": "",
  "stay_limit": "협정상의 체류기간",
  "delegated_to": null,
  "program_ids": [],
  "sub_codes": [],
  "confidence": "high",
  "notes": "",
  "status": "active"
 },
 {
  "qualification_id": "Q:H-2",
  "parent_qualification_id": null,
  "manual_type": "both",
  "group": "H",
  "code": "H-2",
  "name_ko": "방문취업",
  "activity_scope": "",
  "eligible_persons": "",
  "stay_limit": "3년",
  "delegated_to": "PG:DONGPO",
  "program_ids": [
   "PG:DONGPO"
  ],
  "sub_codes": [],
  "confidence": "high",
  "notes": "사증 본편 챕터 없음('※ 38.번참조') — 동포매뉴얼 위임.",
  "status": "active"
 },
 {
  "qualification_id": "Q:C-3-8",
  "parent_qualification_id": "Q:C-3",
  "manual_type": "both",
  "group": "C",
  "code": "C-3-8",
  "name_ko": "동포방문",
  "activity_scope": "",
  "eligible_persons": "",
  "stay_limit": "90일",
  "delegated_to": null,
  "program_ids": [
   "PG:DONGPO"
  ],
  "sub_codes": [],
  "confidence": "high",
  "notes": "상세는 동포매뉴얼(본편 C-3 챕터는 약호표 언급뿐  답변). '26.2.12 제도 폐지  경로는 abolished 유지.",
  "status": "active"
 },
 {
  "qualification_id": "Q:E-7-S1",
  "parent_qualification_id": "Q:E-7",
  "manual_type": "both",
  "group": "E",
  "code": "E-7-S1",
  "name_ko": "네거티브방식 전문인력(고소득)",
  "activity_scope": "",
  "eligible_persons": "",
  "stay_limit": "3년",
  "delegated_to": null,
  "program_ids": [],
  "sub_codes": [],
  "confidence": "high",
  "notes": "소득이 전년도 1인당 GNI 3배 이상인 전문인력  학력·경력·분야 무관, 제한직종 외, 국민고용보호 비적용. S1/S2 실무상 완전히 다름 → 분리.",
  "status": "active"
 },
 {
  "qualification_id": "Q:E-7-S2",
  "parent_qualification_id": "Q:E-7",
  "manual_type": "both",
  "group": "E",
  "code": "E-7-S2",
  "name_ko": "네거티브방식 전문인력(첨단산업)",
  "activity_scope": "",
  "eligible_persons": "",
  "stay_limit": "3년",
  "delegated_to": null,
  "program_ids": [],
  "sub_codes": [],
  "confidence": "high",
  "notes": "점수 60점 + GNI 1배 + 첨단산업(산업발전법 §5 고시, 산업통상자원부 고시 제2022-36호 3,043개 첨단기술 제품 일치 한정, 필요 시 '첨단기술 제품 확인서' 확인). 국민고용보호 비적용.",
  "status": "active"
 },
 {
  "qualification_id": "Q:F-1-23",
  "parent_qualification_id": "Q:F-1",
  "manual_type": "both",
  "group": "F",
  "code": "F-1-23",
  "name_ko": "첨단투자자의 외국인 가사보조인(방문동거)",
  "activity_scope": "",
  "eligible_persons": "가사보조인 묶음(F-1-22 고액투자자·F-1-23 첨단투자자·F-1-24 전문인력) 중 '첨단투자자'가 고용한 가사보조인",
  "stay_limit": "2년",
  "delegated_to": null,
  "program_ids": [],
  "sub_codes": [],
  "confidence": "high",
  "notes": "매뉴얼 기준 확인: «3. 투자가 및 전문인력의 외국인 가사보조인(F-1-22, F-1-23, F-1-24) … 사증발급 (고액투자자  F-1-22, 첨단투자자  F-1-23, 전문인력  F-1-24) - 공관장 재량으로 체류자격 방문동거(F-1), 체류기간 1년 이하의 단수사증 발급»",
  "status": "active"
 },
 {
  "qualification_id": "Q:F-2-T",
  "parent_qualification_id": "Q:F-2",
  "manual_type": "both",
  "group": "F",
  "code": "F-2-T",
  "name_ko": "탑티어 거주",
  "activity_scope": "",
  "eligible_persons": "",
  "stay_limit": "5년",
  "delegated_to": null,
  "program_ids": [
   "PG:TOP_TIER"
  ],
  "sub_codes": [],
  "confidence": "high",
  "notes": "탑티어 트랙 3단계.",
  "status": "active"
 },
 {
  "qualification_id": "Q:D-10-T",
  "parent_qualification_id": "Q:D-10",
  "manual_type": "both",
  "group": "D",
  "code": "D-10-T",
  "name_ko": "탑티어 구직",
  "activity_scope": "",
  "eligible_persons": "",
  "stay_limit": "1년",
  "delegated_to": null,
  "program_ids": [
   "PG:TOP_TIER"
  ],
  "sub_codes": [],
  "confidence": "medium",
  "notes": "탑티어 트랙 1단계.",
  "status": "active"
 },
 {
  "qualification_id": "Q:E-7-T",
  "parent_qualification_id": "Q:E-7",
  "manual_type": "both",
  "group": "E",
  "code": "E-7-T",
  "name_ko": "탑티어 취업",
  "activity_scope": "",
  "eligible_persons": "",
  "stay_limit": "3년",
  "delegated_to": null,
  "program_ids": [
   "PG:TOP_TIER"
  ],
  "sub_codes": [],
  "confidence": "medium",
  "notes": "탑티어 트랙 2단계.",
  "status": "active"
 },
 {
  "qualification_id": "Q:F-5-T",
  "parent_qualification_id": "Q:F-5",
  "manual_type": "both",
  "group": "F",
  "code": "F-5-T",
  "name_ko": "탑티어 영주",
  "activity_scope": "",
  "eligible_persons": "",
  "stay_limit": "상한 없음",
  "delegated_to": null,
  "program_ids": [
   "PG:TOP_TIER"
  ],
  "sub_codes": [],
  "confidence": "medium",
  "notes": "탑티어 트랙 4단계.",
  "status": "active"
 },
 {
  "qualification_id": "Q:F-2-7S",
  "parent_qualification_id": "Q:F-2",
  "manual_type": "both",
  "group": "F",
  "code": "F-2-7S",
  "name_ko": "K-STAR 거주",
  "activity_scope": "",
  "eligible_persons": "",
  "stay_limit": "5년",
  "delegated_to": null,
  "program_ids": [
   "PG:K_STAR"
  ],
  "sub_codes": [],
  "confidence": "medium",
  "notes": "K-STAR 트랙 2단계.",
  "status": "active"
 },
 {
  "qualification_id": "Q:F-5-S1",
  "parent_qualification_id": "Q:F-5",
  "manual_type": "both",
  "group": "F",
  "code": "F-5-S1",
  "name_ko": "K-STAR 영주",
  "activity_scope": "",
  "eligible_persons": "",
  "stay_limit": "상한 없음",
  "delegated_to": null,
  "program_ids": [
   "PG:K_STAR"
  ],
  "sub_codes": [],
  "confidence": "medium",
  "notes": "K-STAR 트랙 3단계(특별귀화 병행).",
  "status": "active"
 },
 {
  "qualification_id": "Q:F-5-S2",
  "parent_qualification_id": "Q:F-5",
  "manual_type": "both",
  "group": "F",
  "code": "F-5-S2",
  "name_ko": "K-STAR 영주(구분2)",
  "activity_scope": "",
  "eligible_persons": "",
  "stay_limit": "상한 없음",
  "delegated_to": null,
  "program_ids": [
   "PG:K_STAR"
  ],
  "sub_codes": [],
  "confidence": "low",
  "notes": "세부 구분 매뉴얼 기준 확인 필요.",
  "status": "active"
 },
 {
  "qualification_id": "Q:F-2-R",
  "parent_qualification_id": "Q:F-2",
  "manual_type": "both",
  "group": "F",
  "code": "F-2-R",
  "name_ko": "지역특화형 거주",
  "activity_scope": "",
  "eligible_persons": "",
  "stay_limit": "5년",
  "delegated_to": null,
  "program_ids": [
   "PG:REGIONAL",
   "PG:YOUTH_SETTLE"
  ],
  "sub_codes": [],
  "confidence": "medium",
  "notes": "지역특화형비자(지자체 추천).",
  "status": "active"
 },
 {
  "qualification_id": "Q:F-4-R",
  "parent_qualification_id": "Q:F-4",
  "manual_type": "both",
  "group": "F",
  "code": "F-4-R",
  "name_ko": "지역특화형 재외동포",
  "activity_scope": "",
  "eligible_persons": "",
  "stay_limit": "3년",
  "delegated_to": null,
  "program_ids": [
   "PG:REGIONAL"
  ],
  "sub_codes": [],
  "confidence": "medium",
  "notes": "",
  "status": "active"
 },
 {
  "qualification_id": "Q:E-7-Y",
  "parent_qualification_id": "Q:E-7",
  "manual_type": "both",
  "group": "E",
  "code": "E-7-Y",
  "name_ko": "국내성장 청소년 취업",
  "activity_scope": "",
  "eligible_persons": "",
  "stay_limit": "3년",
  "delegated_to": null,
  "program_ids": [
   "PG:YOUTH_SETTLE"
  ],
  "sub_codes": [],
  "confidence": "medium",
  "notes": "청소년 취업·정주 트랙 2단계.",
  "status": "active"
 },
 {
  "qualification_id": "Q:F-2-71",
  "parent_qualification_id": "Q:F-2",
  "manual_type": "both",
  "group": "F",
  "code": "F-2-71",
  "name_ko": "K-STAR 관련 거주",
  "activity_scope": "",
  "eligible_persons": "",
  "stay_limit": "5년",
  "delegated_to": null,
  "program_ids": [
   "PG:K_STAR"
  ],
  "sub_codes": [],
  "confidence": "low",
  "notes": "",
  "status": "active"
 },
 {
  "qualification_id": "Q:D-4-5",
  "parent_qualification_id": "Q:D-4",
  "manual_type": "both",
  "group": "D",
  "code": "D-4-5",
  "name_ko": "한식조리연수",
  "activity_scope": "",
  "eligible_persons": "",
  "stay_limit": "2년",
  "delegated_to": null,
  "program_ids": [],
  "sub_codes": [],
  "confidence": "medium",
  "notes": "v2 M1-0372에서 사증/체류 분리.",
  "status": "active"
 },
 {
  "qualification_id": "Q:E-7-4",
  "parent_qualification_id": "Q:E-7",
  "manual_type": "both",
  "group": "E",
  "code": "E-7-4",
  "name_ko": "숙련기능인력(점수제)",
  "activity_scope": "",
  "eligible_persons": "",
  "stay_limit": "3년",
  "delegated_to": null,
  "program_ids": [],
  "sub_codes": [],
  "confidence": "high",
  "notes": "변경허가 예외 경로: 뿌리산업 숙련기능공 등 기량검증·쿼터 선발(조선용접공 절차 준용).",
  "status": "active"
 },
 {
  "qualification_id": "Q:D-10-1",
  "parent_qualification_id": "Q:D-10",
  "manual_type": "both",
  "group": "D",
  "code": "D-10-1",
  "name_ko": "구직",
  "activity_scope": "",
  "eligible_persons": "",
  "stay_limit": "1년",
  "delegated_to": null,
  "program_ids": [],
  "sub_codes": [],
  "confidence": "medium",
  "notes": "명칭은 v2 업무명 유래  매뉴얼 매뉴얼 기준 명칭 대조 필요.",
  "status": "active"
 },
 {
  "qualification_id": "Q:D-10-2",
  "parent_qualification_id": "Q:D-10",
  "manual_type": "both",
  "group": "D",
  "code": "D-10-2",
  "name_ko": "기술 창업준비",
  "activity_scope": "",
  "eligible_persons": "",
  "stay_limit": "1년",
  "delegated_to": null,
  "program_ids": [],
  "sub_codes": [],
  "confidence": "medium",
  "notes": "명칭은 v2 업무명 유래  매뉴얼 매뉴얼 기준 명칭 대조 필요.",
  "status": "active"
 },
 {
  "qualification_id": "Q:D-10-3",
  "parent_qualification_id": "Q:D-10",
  "manual_type": "both",
  "group": "D",
  "code": "D-10-3",
  "name_ko": "첨단기술인턴",
  "activity_scope": "",
  "eligible_persons": "",
  "stay_limit": "1년",
  "delegated_to": null,
  "program_ids": [],
  "sub_codes": [],
  "confidence": "medium",
  "notes": "명칭은 v2 업무명 유래  매뉴얼 매뉴얼 기준 명칭 대조 필요.",
  "status": "active"
 },
 {
  "qualification_id": "Q:D-2-1",
  "parent_qualification_id": "Q:D-2",
  "manual_type": "both",
  "group": "D",
  "code": "D-2-1",
  "name_ko": "전문학사과정 유학",
  "activity_scope": "",
  "eligible_persons": "",
  "stay_limit": "2년",
  "delegated_to": null,
  "program_ids": [],
  "sub_codes": [],
  "confidence": "medium",
  "notes": "명칭은 v2 업무명 유래  매뉴얼 매뉴얼 기준 명칭 대조 필요.",
  "status": "active"
 },
 {
  "qualification_id": "Q:D-2-2",
  "parent_qualification_id": "Q:D-2",
  "manual_type": "both",
  "group": "D",
  "code": "D-2-2",
  "name_ko": "학사과정 유학",
  "activity_scope": "",
  "eligible_persons": "",
  "stay_limit": "2년",
  "delegated_to": null,
  "program_ids": [],
  "sub_codes": [],
  "confidence": "medium",
  "notes": "명칭은 v2 업무명 유래  매뉴얼 매뉴얼 기준 명칭 대조 필요.",
  "status": "active"
 },
 {
  "qualification_id": "Q:D-2-3",
  "parent_qualification_id": "Q:D-2",
  "manual_type": "both",
  "group": "D",
  "code": "D-2-3",
  "name_ko": "석사과정 유학",
  "activity_scope": "",
  "eligible_persons": "",
  "stay_limit": "2년",
  "delegated_to": null,
  "program_ids": [],
  "sub_codes": [],
  "confidence": "medium",
  "notes": "명칭은 v2 업무명 유래  매뉴얼 매뉴얼 기준 명칭 대조 필요.",
  "status": "active"
 },
 {
  "qualification_id": "Q:D-2-4",
  "parent_qualification_id": "Q:D-2",
  "manual_type": "both",
  "group": "D",
  "code": "D-2-4",
  "name_ko": "박사과정 유학",
  "activity_scope": "",
  "eligible_persons": "",
  "stay_limit": "2년",
  "delegated_to": null,
  "program_ids": [],
  "sub_codes": [],
  "confidence": "medium",
  "notes": "명칭은 v2 업무명 유래  매뉴얼 매뉴얼 기준 명칭 대조 필요.",
  "status": "active"
 },
 {
  "qualification_id": "Q:D-2-5",
  "parent_qualification_id": "Q:D-2",
  "manual_type": "both",
  "group": "D",
  "code": "D-2-5",
  "name_ko": "연구과정 유학",
  "activity_scope": "",
  "eligible_persons": "",
  "stay_limit": "2년",
  "delegated_to": null,
  "program_ids": [],
  "sub_codes": [],
  "confidence": "medium",
  "notes": "명칭은 v2 업무명 유래  매뉴얼 매뉴얼 기준 명칭 대조 필요.",
  "status": "active"
 },
 {
  "qualification_id": "Q:D-2-6",
  "parent_qualification_id": "Q:D-2",
  "manual_type": "both",
  "group": "D",
  "code": "D-2-6",
  "name_ko": "교환학생 유학",
  "activity_scope": "",
  "eligible_persons": "",
  "stay_limit": "2년",
  "delegated_to": null,
  "program_ids": [],
  "sub_codes": [],
  "confidence": "medium",
  "notes": "명칭은 v2 업무명 유래  매뉴얼 매뉴얼 기준 명칭 대조 필요.",
  "status": "active"
 },
 {
  "qualification_id": "Q:D-2-7",
  "parent_qualification_id": "Q:D-2",
  "manual_type": "both",
  "group": "D",
  "code": "D-2-7",
  "name_ko": "일-학습 연계 유학",
  "activity_scope": "",
  "eligible_persons": "",
  "stay_limit": "2년",
  "delegated_to": null,
  "program_ids": [],
  "sub_codes": [],
  "confidence": "medium",
  "notes": "명칭은 v2 업무명 유래  매뉴얼 매뉴얼 기준 명칭 대조 필요.",
  "status": "active"
 },
 {
  "qualification_id": "Q:D-2-8",
  "parent_qualification_id": "Q:D-2",
  "manual_type": "both",
  "group": "D",
  "code": "D-2-8",
  "name_ko": "방문학생",
  "activity_scope": "",
  "eligible_persons": "",
  "stay_limit": "2년",
  "delegated_to": null,
  "program_ids": [],
  "sub_codes": [],
  "confidence": "medium",
  "notes": "명칭은 v2 업무명 유래  매뉴얼 매뉴얼 기준 명칭 대조 필요.",
  "status": "active"
 },
 {
  "qualification_id": "Q:D-4-1",
  "parent_qualification_id": "Q:D-4",
  "manual_type": "both",
  "group": "D",
  "code": "D-4-1",
  "name_ko": "한국어연수",
  "activity_scope": "",
  "eligible_persons": "",
  "stay_limit": "2년",
  "delegated_to": null,
  "program_ids": [],
  "sub_codes": [],
  "confidence": "medium",
  "notes": "명칭은 v2 업무명 유래  매뉴얼 매뉴얼 기준 명칭 대조 필요.",
  "status": "active"
 },
 {
  "qualification_id": "Q:D-4-2",
  "parent_qualification_id": "Q:D-4",
  "manual_type": "both",
  "group": "D",
  "code": "D-4-2",
  "name_ko": "졸업생에 대한 일반연수",
  "activity_scope": "",
  "eligible_persons": "",
  "stay_limit": "2년",
  "delegated_to": null,
  "program_ids": [],
  "sub_codes": [],
  "confidence": "medium",
  "notes": "명칭은 v2 업무명 유래  매뉴얼 매뉴얼 기준 명칭 대조 필요.",
  "status": "active"
 },
 {
  "qualification_id": "Q:D-4-7",
  "parent_qualification_id": "Q:D-4",
  "manual_type": "both",
  "group": "D",
  "code": "D-4-7",
  "name_ko": "외국어연수",
  "activity_scope": "",
  "eligible_persons": "",
  "stay_limit": "2년",
  "delegated_to": null,
  "program_ids": [],
  "sub_codes": [],
  "confidence": "medium",
  "notes": "명칭은 v2 업무명 유래  매뉴얼 매뉴얼 기준 명칭 대조 필요.",
  "status": "active"
 },
 {
  "qualification_id": "Q:D-8-1",
  "parent_qualification_id": "Q:D-8",
  "manual_type": "both",
  "group": "D",
  "code": "D-8-1",
  "name_ko": "법인투자",
  "activity_scope": "",
  "eligible_persons": "",
  "stay_limit": "주재활동 5년 · 벤처기업 설립자 2년(예비 벤처기업 6개월)",
  "delegated_to": null,
  "program_ids": [],
  "sub_codes": [],
  "confidence": "medium",
  "notes": "명칭은 v2 업무명 유래  매뉴얼 매뉴얼 기준 명칭 대조 필요.",
  "status": "active"
 },
 {
  "qualification_id": "Q:D-8-2",
  "parent_qualification_id": "Q:D-8",
  "manual_type": "both",
  "group": "D",
  "code": "D-8-2",
  "name_ko": "벤처투자",
  "activity_scope": "",
  "eligible_persons": "",
  "stay_limit": "주재활동 5년 · 벤처기업 설립자 2년(예비 벤처기업 6개월)",
  "delegated_to": null,
  "program_ids": [],
  "sub_codes": [],
  "confidence": "medium",
  "notes": "명칭은 v2 업무명 유래  매뉴얼 매뉴얼 기준 명칭 대조 필요.",
  "status": "active"
 },
 {
  "qualification_id": "Q:D-8-3",
  "parent_qualification_id": "Q:D-8",
  "manual_type": "both",
  "group": "D",
  "code": "D-8-3",
  "name_ko": "개인기업투자",
  "activity_scope": "",
  "eligible_persons": "",
  "stay_limit": "주재활동 5년 · 벤처기업 설립자 2년(예비 벤처기업 6개월)",
  "delegated_to": null,
  "program_ids": [],
  "sub_codes": [],
  "confidence": "medium",
  "notes": "명칭은 v2 업무명 유래  매뉴얼 매뉴얼 기준 명칭 대조 필요.",
  "status": "active"
 },
 {
  "qualification_id": "Q:D-9-1",
  "parent_qualification_id": "Q:D-9",
  "manual_type": "both",
  "group": "D",
  "code": "D-9-1",
  "name_ko": "무역업",
  "activity_scope": "",
  "eligible_persons": "",
  "stay_limit": "2년",
  "delegated_to": null,
  "program_ids": [],
  "sub_codes": [],
  "confidence": "medium",
  "notes": "명칭은 v2 업무명 유래  매뉴얼 매뉴얼 기준 명칭 대조 필요.",
  "status": "active"
 },
 {
  "qualification_id": "Q:D-9-4",
  "parent_qualification_id": "Q:D-9",
  "manual_type": "both",
  "group": "D",
  "code": "D-9-4",
  "name_ko": "개인사업자 무역경영",
  "activity_scope": "",
  "eligible_persons": "",
  "stay_limit": "2년",
  "delegated_to": null,
  "program_ids": [],
  "sub_codes": [],
  "confidence": "medium",
  "notes": "명칭은 v2 업무명 유래  매뉴얼 매뉴얼 기준 명칭 대조 필요.",
  "status": "active"
 },
 {
  "qualification_id": "Q:E-10-2",
  "parent_qualification_id": "Q:E-10",
  "manual_type": "both",
  "group": "E",
  "code": "E-10-2",
  "name_ko": "선원취업",
  "activity_scope": "",
  "eligible_persons": "",
  "stay_limit": "3년",
  "delegated_to": null,
  "program_ids": [],
  "sub_codes": [],
  "confidence": "medium",
  "notes": "명칭은 v2 업무명 유래  매뉴얼 매뉴얼 기준 명칭 대조 필요.",
  "status": "active"
 },
 {
  "qualification_id": "Q:E-7-1",
  "parent_qualification_id": "Q:E-7",
  "manual_type": "both",
  "group": "E",
  "code": "E-7-1",
  "name_ko": "전문인력",
  "activity_scope": "",
  "eligible_persons": "",
  "stay_limit": "3년",
  "delegated_to": null,
  "program_ids": [],
  "sub_codes": [],
  "confidence": "medium",
  "notes": "명칭은 v2 업무명 유래  매뉴얼 매뉴얼 기준 명칭 대조 필요.",
  "status": "active"
 },
 {
  "qualification_id": "Q:E-7-2",
  "parent_qualification_id": "Q:E-7",
  "manual_type": "both",
  "group": "E",
  "code": "E-7-2",
  "name_ko": "준전문인력",
  "activity_scope": "",
  "eligible_persons": "",
  "stay_limit": "3년",
  "delegated_to": null,
  "program_ids": [],
  "sub_codes": [],
  "confidence": "medium",
  "notes": "명칭은 v2 업무명 유래  매뉴얼 매뉴얼 기준 명칭 대조 필요.",
  "status": "active"
 },
 {
  "qualification_id": "Q:E-7-3",
  "parent_qualification_id": "Q:E-7",
  "manual_type": "both",
  "group": "E",
  "code": "E-7-3",
  "name_ko": "일반기능인력",
  "activity_scope": "",
  "eligible_persons": "",
  "stay_limit": "3년",
  "delegated_to": null,
  "program_ids": [],
  "sub_codes": [],
  "confidence": "medium",
  "notes": "명칭은 v2 업무명 유래  매뉴얼 매뉴얼 기준 명칭 대조 필요.",
  "status": "active"
 },
 {
  "qualification_id": "Q:E-7-4R",
  "parent_qualification_id": "Q:E-7",
  "manual_type": "both",
  "group": "E",
  "code": "E-7-4R",
  "name_ko": "지역특화형 숙련기능인력",
  "activity_scope": "",
  "eligible_persons": "",
  "stay_limit": "3년",
  "delegated_to": null,
  "program_ids": [],
  "sub_codes": [],
  "confidence": "medium",
  "notes": "명칭은 v2 업무명 유래  매뉴얼 매뉴얼 기준 명칭 대조 필요.",
  "status": "active"
 },
 {
  "qualification_id": "Q:E-9-1",
  "parent_qualification_id": "Q:E-9",
  "manual_type": "both",
  "group": "E",
  "code": "E-9-1",
  "name_ko": "비전문취업-농축산업",
  "activity_scope": "",
  "eligible_persons": "",
  "stay_limit": "3년",
  "delegated_to": null,
  "program_ids": [],
  "sub_codes": [],
  "confidence": "medium",
  "notes": "명칭은 v2 업무명 유래  매뉴얼 매뉴얼 기준 명칭 대조 필요.",
  "status": "active"
 },
 {
  "qualification_id": "Q:E-9-2",
  "parent_qualification_id": "Q:E-9",
  "manual_type": "both",
  "group": "E",
  "code": "E-9-2",
  "name_ko": "비전문취업-건설업",
  "activity_scope": "",
  "eligible_persons": "",
  "stay_limit": "3년",
  "delegated_to": null,
  "program_ids": [],
  "sub_codes": [],
  "confidence": "medium",
  "notes": "명칭은 v2 업무명 유래  매뉴얼 매뉴얼 기준 명칭 대조 필요.",
  "status": "active"
 },
 {
  "qualification_id": "Q:E-9-3",
  "parent_qualification_id": "Q:E-9",
  "manual_type": "both",
  "group": "E",
  "code": "E-9-3",
  "name_ko": "비전문취업-제조업",
  "activity_scope": "",
  "eligible_persons": "",
  "stay_limit": "3년",
  "delegated_to": null,
  "program_ids": [],
  "sub_codes": [],
  "confidence": "medium",
  "notes": "명칭은 v2 업무명 유래  매뉴얼 매뉴얼 기준 명칭 대조 필요.",
  "status": "active"
 },
 {
  "qualification_id": "Q:E-9-4",
  "parent_qualification_id": "Q:E-9",
  "manual_type": "both",
  "group": "E",
  "code": "E-9-4",
  "name_ko": "비전문취업-어업",
  "activity_scope": "",
  "eligible_persons": "",
  "stay_limit": "3년",
  "delegated_to": null,
  "program_ids": [],
  "sub_codes": [],
  "confidence": "medium",
  "notes": "명칭은 v2 업무명 유래  매뉴얼 매뉴얼 기준 명칭 대조 필요.",
  "status": "active"
 },
 {
  "qualification_id": "Q:E-9-5",
  "parent_qualification_id": "Q:E-9",
  "manual_type": "both",
  "group": "E",
  "code": "E-9-5",
  "name_ko": "비전문취업-서비스업",
  "activity_scope": "",
  "eligible_persons": "",
  "stay_limit": "3년",
  "delegated_to": null,
  "program_ids": [],
  "sub_codes": [],
  "confidence": "medium",
  "notes": "명칭은 v2 업무명 유래  매뉴얼 매뉴얼 기준 명칭 대조 필요.",
  "status": "active"
 },
 {
  "qualification_id": "Q:F-1-11",
  "parent_qualification_id": "Q:F-1",
  "manual_type": "both",
  "group": "F",
  "code": "F-1-11",
  "name_ko": "방문취업자 가족 방문동거",
  "activity_scope": "",
  "eligible_persons": "",
  "stay_limit": "2년",
  "delegated_to": null,
  "program_ids": [],
  "sub_codes": [],
  "confidence": "medium",
  "notes": "명칭은 v2 업무명 유래  매뉴얼 매뉴얼 기준 명칭 대조 필요. | [260709 재편] 260709 매뉴얼에서 신규 발급 근거 소멸 — 대체 코드: F-3-20(방문취업(H-2) 가족 동반, 체류 p425·사증 p318). 구 코드 이력 보존용으로 유지하며 신규 선택 목록에는 노출하지 않음(라우터 children 목록 제외). 체류매뉴얼 p626(지역특화 동포)에 기존 소지자 경과 언급만 잔존.",
  "status": "deprecated"
 },
 {
  "qualification_id": "Q:F-1-15",
  "parent_qualification_id": "Q:F-1",
  "manual_type": "both",
  "group": "F",
  "code": "F-1-15",
  "name_ko": "우수인재·투자자·유학생 부모 방문동거",
  "activity_scope": "",
  "eligible_persons": "",
  "stay_limit": "2년",
  "delegated_to": null,
  "program_ids": [],
  "sub_codes": [],
  "confidence": "medium",
  "notes": "명칭은 v2 업무명 유래  매뉴얼 매뉴얼 기준 명칭 대조 필요.",
  "status": "active"
 },
 {
  "qualification_id": "Q:F-1-16",
  "parent_qualification_id": "Q:F-1",
  "manual_type": "both",
  "group": "F",
  "code": "F-1-16",
  "name_ko": "난민인정자 가족 방문동거",
  "activity_scope": "",
  "eligible_persons": "",
  "stay_limit": "2년",
  "delegated_to": null,
  "program_ids": [],
  "sub_codes": [],
  "confidence": "medium",
  "notes": "명칭은 v2 업무명 유래  매뉴얼 매뉴얼 기준 명칭 대조 필요.",
  "status": "active"
 },
 {
  "qualification_id": "Q:F-1-21",
  "parent_qualification_id": "Q:F-1",
  "manual_type": "both",
  "group": "F",
  "code": "F-1-21",
  "name_ko": "주한 외국공관원 가사보조인",
  "activity_scope": "",
  "eligible_persons": "",
  "stay_limit": "2년",
  "delegated_to": null,
  "program_ids": [],
  "sub_codes": [],
  "confidence": "medium",
  "notes": "명칭은 v2 업무명 유래  매뉴얼 매뉴얼 기준 명칭 대조 필요.",
  "status": "active"
 },
 {
  "qualification_id": "Q:F-1-22",
  "parent_qualification_id": "Q:F-1",
  "manual_type": "both",
  "group": "F",
  "code": "F-1-22",
  "name_ko": "고액투자가 가사보조인",
  "activity_scope": "",
  "eligible_persons": "",
  "stay_limit": "2년",
  "delegated_to": null,
  "program_ids": [],
  "sub_codes": [],
  "confidence": "medium",
  "notes": "명칭은 v2 업무명 유래  매뉴얼 매뉴얼 기준 명칭 대조 필요.",
  "status": "active"
 },
 {
  "qualification_id": "Q:F-1-24",
  "parent_qualification_id": "Q:F-1",
  "manual_type": "both",
  "group": "F",
  "code": "F-1-24",
  "name_ko": "해외우수인재 가사보조인",
  "activity_scope": "",
  "eligible_persons": "",
  "stay_limit": "2년",
  "delegated_to": null,
  "program_ids": [],
  "sub_codes": [],
  "confidence": "medium",
  "notes": "명칭은 v2 업무명 유래  매뉴얼 매뉴얼 기준 명칭 대조 필요.",
  "status": "active"
 },
 {
  "qualification_id": "Q:F-1-4",
  "parent_qualification_id": "Q:F-1",
  "manual_type": "both",
  "group": "F",
  "code": "F-1-4",
  "name_ko": "혼외 미성년 자녀 양육자",
  "activity_scope": "",
  "eligible_persons": "",
  "stay_limit": "2년",
  "delegated_to": null,
  "program_ids": [],
  "sub_codes": [],
  "confidence": "medium",
  "notes": "명칭은 v2 업무명 유래  매뉴얼 매뉴얼 기준 명칭 대조 필요.",
  "status": "active"
 },
 {
  "qualification_id": "Q:F-1-5",
  "parent_qualification_id": "Q:F-1",
  "manual_type": "both",
  "group": "F",
  "code": "F-1-5",
  "name_ko": "결혼이민자의 부모 등 가족 방문동거",
  "activity_scope": "",
  "eligible_persons": "",
  "stay_limit": "2년",
  "delegated_to": null,
  "program_ids": [],
  "sub_codes": [],
  "confidence": "medium",
  "notes": "명칭은 v2 업무명 유래  매뉴얼 매뉴얼 기준 명칭 대조 필요.",
  "status": "active"
 },
 {
  "qualification_id": "Q:F-1-51",
  "parent_qualification_id": "Q:F-1",
  "manual_type": "both",
  "group": "F",
  "code": "F-1-51",
  "name_ko": "국제입양 아동",
  "activity_scope": "",
  "eligible_persons": "",
  "stay_limit": "2년",
  "delegated_to": null,
  "program_ids": [],
  "sub_codes": [],
  "confidence": "medium",
  "notes": "명칭은 v2 업무명 유래  매뉴얼 매뉴얼 기준 명칭 대조 필요.",
  "status": "active"
 },
 {
  "qualification_id": "Q:F-1-52",
  "parent_qualification_id": "Q:F-1",
  "manual_type": "both",
  "group": "F",
  "code": "F-1-52",
  "name_ko": "결혼이민자의 전혼관계 출생 미성년 자녀 방문동거",
  "activity_scope": "",
  "eligible_persons": "",
  "stay_limit": "2년",
  "delegated_to": null,
  "program_ids": [],
  "sub_codes": [],
  "confidence": "medium",
  "notes": "명칭은 v2 업무명 유래  매뉴얼 매뉴얼 기준 명칭 대조 필요.",
  "status": "active"
 },
 {
  "qualification_id": "Q:F-1-6",
  "parent_qualification_id": "Q:F-1",
  "manual_type": "both",
  "group": "F",
  "code": "F-1-6",
  "name_ko": "혼인단절 가사정리",
  "activity_scope": "",
  "eligible_persons": "",
  "stay_limit": "2년",
  "delegated_to": null,
  "program_ids": [],
  "sub_codes": [],
  "confidence": "medium",
  "notes": "명칭은 v2 업무명 유래  매뉴얼 매뉴얼 기준 명칭 대조 필요.",
  "status": "active"
 },
 {
  "qualification_id": "Q:F-1-9",
  "parent_qualification_id": "Q:F-1",
  "manual_type": "both",
  "group": "F",
  "code": "F-1-9",
  "name_ko": "재외동포 가족 방문동거",
  "activity_scope": "",
  "eligible_persons": "",
  "stay_limit": "2년",
  "delegated_to": null,
  "program_ids": [],
  "sub_codes": [],
  "confidence": "medium",
  "notes": "명칭은 v2 업무명 유래  매뉴얼 매뉴얼 기준 명칭 대조 필요. | [260709 재편] 260709 매뉴얼에서 신규 발급 근거 소멸 — 대체 코드: F-3-19(재외동포(F-4) 가족 동반, 체류 p425·사증 p318). 구 코드 이력 보존용으로 유지하며 신규 선택 목록에는 노출하지 않음(라우터 children 목록 제외).",
  "status": "deprecated"
 },
 {
  "qualification_id": "Q:F-2-3",
  "parent_qualification_id": "Q:F-2",
  "manual_type": "both",
  "group": "F",
  "code": "F-2-3",
  "name_ko": "영주자의 배우자 및 미성년자녀 거주",
  "activity_scope": "",
  "eligible_persons": "",
  "stay_limit": "5년",
  "delegated_to": null,
  "program_ids": [],
  "sub_codes": [],
  "confidence": "medium",
  "notes": "명칭은 v2 업무명 유래  매뉴얼 매뉴얼 기준 명칭 대조 필요.",
  "status": "active"
 },
 {
  "qualification_id": "Q:F-2-4",
  "parent_qualification_id": "Q:F-2",
  "manual_type": "both",
  "group": "F",
  "code": "F-2-4",
  "name_ko": "난민인정자 거주",
  "activity_scope": "",
  "eligible_persons": "",
  "stay_limit": "5년",
  "delegated_to": null,
  "program_ids": [],
  "sub_codes": [],
  "confidence": "medium",
  "notes": "명칭은 v2 업무명 유래  매뉴얼 매뉴얼 기준 명칭 대조 필요.",
  "status": "active"
 },
 {
  "qualification_id": "Q:F-2-5",
  "parent_qualification_id": "Q:F-2",
  "manual_type": "both",
  "group": "F",
  "code": "F-2-5",
  "name_ko": "고액투자자 거주",
  "activity_scope": "",
  "eligible_persons": "",
  "stay_limit": "5년",
  "delegated_to": null,
  "program_ids": [],
  "sub_codes": [],
  "confidence": "medium",
  "notes": "명칭은 v2 업무명 유래  매뉴얼 매뉴얼 기준 명칭 대조 필요.",
  "status": "active"
 },
 {
  "qualification_id": "Q:F-2-6",
  "parent_qualification_id": "Q:F-2",
  "manual_type": "both",
  "group": "F",
  "code": "F-2-6",
  "name_ko": "숙련 생산기능 외국인력 거주",
  "activity_scope": "",
  "eligible_persons": "",
  "stay_limit": "5년",
  "delegated_to": null,
  "program_ids": [],
  "sub_codes": [],
  "confidence": "medium",
  "notes": "명칭은 v2 업무명 유래  매뉴얼 매뉴얼 기준 명칭 대조 필요.",
  "status": "active"
 },
 {
  "qualification_id": "Q:F-2-7",
  "parent_qualification_id": "Q:F-2",
  "manual_type": "both",
  "group": "F",
  "code": "F-2-7",
  "name_ko": "점수제 우수인재 거주",
  "activity_scope": "",
  "eligible_persons": "",
  "stay_limit": "5년",
  "delegated_to": null,
  "program_ids": [],
  "sub_codes": [],
  "confidence": "medium",
  "notes": "명칭은 v2 업무명 유래  매뉴얼 매뉴얼 기준 명칭 대조 필요.",
  "status": "active"
 },
 {
  "qualification_id": "Q:F-2-99",
  "parent_qualification_id": "Q:F-2",
  "manual_type": "both",
  "group": "F",
  "code": "F-2-99",
  "name_ko": "기타 장기체류자 거주",
  "activity_scope": "",
  "eligible_persons": "",
  "stay_limit": "5년",
  "delegated_to": null,
  "program_ids": [],
  "sub_codes": [],
  "confidence": "medium",
  "notes": "명칭은 v2 업무명 유래  매뉴얼 매뉴얼 기준 명칭 대조 필요.",
  "status": "active"
 },
 {
  "qualification_id": "Q:F-3-18",
  "parent_qualification_id": "Q:F-3",
  "manual_type": "both",
  "group": "F",
  "code": "F-3-18",
  "name_ko": "기타 장기체류자 동반가족",
  "activity_scope": "",
  "eligible_persons": "기타 장기체류자의 동반가족(배우자·미성년 자녀 등) / 점수제 우수인재(F-2-7)의 배우자·미성년 자녀 중 주체류자 소득요건(GNI) 미충족자(90일 단수사증)",
  "stay_limit": "동반 대상 본인의 체류자격별 상한에 따름",
  "delegated_to": null,
  "program_ids": [],
  "sub_codes": [],
  "confidence": "medium",
  "notes": "[260709 보완] 점수제 우수인재(F-2-7)의 배우자·미성년 자녀: 90일 단수사증(F-3-18) — 상세는 점수제 우수인재 거주(F-2) 지침('22.3.28)에 따름(사증매뉴얼 p314·p318). 사증발급인정 절차에서 주체류자 소득(GNI) 미충족 시 F-2-71 대신 F-3-18 발급. 서류가 지침 위임이라 별도 사증 route 레코드는 만들지 않음(F-3 공통 경로 참조). 명칭은 v2 업무명 유래.",
  "status": "active"
 },
 {
  "qualification_id": "Q:F-3-1R",
  "parent_qualification_id": "Q:F-3",
  "manual_type": "both",
  "group": "F",
  "code": "F-3-1R",
  "name_ko": "지역특화형 우수인재가족",
  "activity_scope": "",
  "eligible_persons": "",
  "stay_limit": "동반 대상 본인의 체류자격별 상한에 따름",
  "delegated_to": null,
  "program_ids": [],
  "sub_codes": [],
  "confidence": "medium",
  "notes": "명칭은 v2 업무명 유래  매뉴얼 매뉴얼 기준 명칭 대조 필요.",
  "status": "active"
 },
 {
  "qualification_id": "Q:F-3-2R",
  "parent_qualification_id": "Q:F-3",
  "manual_type": "both",
  "group": "F",
  "code": "F-3-2R",
  "name_ko": "지역동포가족",
  "activity_scope": "",
  "eligible_persons": "",
  "stay_limit": "동반 대상 본인의 체류자격별 상한에 따름",
  "delegated_to": null,
  "program_ids": [],
  "sub_codes": [],
  "confidence": "medium",
  "notes": "명칭은 v2 업무명 유래  매뉴얼 매뉴얼 기준 명칭 대조 필요.",
  "status": "active"
 },
 {
  "qualification_id": "Q:F-3-3R",
  "parent_qualification_id": "Q:F-3",
  "manual_type": "both",
  "group": "F",
  "code": "F-3-3R",
  "name_ko": "지역특화형 숙련기능인력가족",
  "activity_scope": "",
  "eligible_persons": "",
  "stay_limit": "동반 대상 본인의 체류자격별 상한에 따름",
  "delegated_to": null,
  "program_ids": [],
  "sub_codes": [],
  "confidence": "medium",
  "notes": "명칭은 v2 업무명 유래  매뉴얼 매뉴얼 기준 명칭 대조 필요.",
  "status": "active"
 },
 {
  "qualification_id": "Q:F-4-19",
  "parent_qualification_id": "Q:F-4",
  "manual_type": "both",
  "group": "F",
  "code": "F-4-19",
  "name_ko": "재외동포 체류자격 변경 (F-4-19)",
  "activity_scope": "",
  "eligible_persons": "",
  "stay_limit": "3년",
  "delegated_to": null,
  "program_ids": [],
  "sub_codes": [],
  "confidence": "medium",
  "notes": "명칭은 v2 업무명 유래  매뉴얼 매뉴얼 기준 명칭 대조 필요.",
  "status": "active"
 },
 {
  "qualification_id": "Q:F-5-1",
  "parent_qualification_id": "Q:F-5",
  "manual_type": "both",
  "group": "F",
  "code": "F-5-1",
  "name_ko": "영주 변경 — 국민의 배우자·자녀 (5년 이상 합법체류)",
  "activity_scope": "",
  "eligible_persons": "",
  "stay_limit": "상한 없음",
  "delegated_to": null,
  "program_ids": [],
  "sub_codes": [],
  "confidence": "medium",
  "notes": "명칭은 v2 업무명 유래  매뉴얼 매뉴얼 기준 명칭 대조 필요.",
  "status": "active"
 },
 {
  "qualification_id": "Q:F-5-10",
  "parent_qualification_id": "Q:F-5",
  "manual_type": "both",
  "group": "F",
  "code": "F-5-10",
  "name_ko": "영주 변경 — 재외동포(F-4) 2년 이상 체류",
  "activity_scope": "",
  "eligible_persons": "",
  "stay_limit": "상한 없음",
  "delegated_to": null,
  "program_ids": [],
  "sub_codes": [],
  "confidence": "medium",
  "notes": "명칭은 v2 업무명 유래  매뉴얼 매뉴얼 기준 명칭 대조 필요.",
  "status": "active"
 },
 {
  "qualification_id": "Q:F-5-11",
  "parent_qualification_id": "Q:F-5",
  "manual_type": "both",
  "group": "F",
  "code": "F-5-11",
  "name_ko": "영주 변경 — 특정분야 능력소유자 (점수제 우수인재)",
  "activity_scope": "",
  "eligible_persons": "",
  "stay_limit": "상한 없음",
  "delegated_to": null,
  "program_ids": [],
  "sub_codes": [],
  "confidence": "medium",
  "notes": "명칭은 v2 업무명 유래  매뉴얼 매뉴얼 기준 명칭 대조 필요.",
  "status": "active"
 },
 {
  "qualification_id": "Q:F-5-14",
  "parent_qualification_id": "Q:F-5",
  "manual_type": "both",
  "group": "F",
  "code": "F-5-14",
  "name_ko": "영주 변경 — 방문취업(H-2) 제조업 4년 이상 근무",
  "activity_scope": "",
  "eligible_persons": "",
  "stay_limit": "상한 없음",
  "delegated_to": null,
  "program_ids": [],
  "sub_codes": [],
  "confidence": "medium",
  "notes": "명칭은 v2 업무명 유래  매뉴얼 매뉴얼 기준 명칭 대조 필요.",
  "status": "active"
 },
 {
  "qualification_id": "Q:F-5-2",
  "parent_qualification_id": "Q:F-5",
  "manual_type": "both",
  "group": "F",
  "code": "F-5-2",
  "name_ko": "영주 변경 — 영주권자의 미성년 자녀",
  "activity_scope": "",
  "eligible_persons": "",
  "stay_limit": "상한 없음",
  "delegated_to": null,
  "program_ids": [],
  "sub_codes": [],
  "confidence": "medium",
  "notes": "명칭은 v2 업무명 유래  매뉴얼 매뉴얼 기준 명칭 대조 필요.",
  "status": "active"
 },
 {
  "qualification_id": "Q:F-5-6",
  "parent_qualification_id": "Q:F-5",
  "manual_type": "both",
  "group": "F",
  "code": "F-5-6",
  "name_ko": "영주 변경 — 결혼이민자 (F-6 → F-5)",
  "activity_scope": "",
  "eligible_persons": "",
  "stay_limit": "상한 없음",
  "delegated_to": null,
  "program_ids": [],
  "sub_codes": [],
  "confidence": "medium",
  "notes": "명칭은 v2 업무명 유래  매뉴얼 매뉴얼 기준 명칭 대조 필요.",
  "status": "active"
 },
 {
  "qualification_id": "Q:F-6-1",
  "parent_qualification_id": "Q:F-6",
  "manual_type": "both",
  "group": "F",
  "code": "F-6-1",
  "name_ko": "국민의 배우자",
  "activity_scope": "",
  "eligible_persons": "",
  "stay_limit": "3년",
  "delegated_to": null,
  "program_ids": [],
  "sub_codes": [],
  "confidence": "medium",
  "notes": "명칭은 v2 업무명 유래  매뉴얼 매뉴얼 기준 명칭 대조 필요.",
  "status": "active"
 },
 {
  "qualification_id": "Q:F-6-2",
  "parent_qualification_id": "Q:F-6",
  "manual_type": "both",
  "group": "F",
  "code": "F-6-2",
  "name_ko": "자녀양육자",
  "activity_scope": "",
  "eligible_persons": "",
  "stay_limit": "3년",
  "delegated_to": null,
  "program_ids": [],
  "sub_codes": [],
  "confidence": "medium",
  "notes": "명칭은 v2 업무명 유래  매뉴얼 매뉴얼 기준 명칭 대조 필요.",
  "status": "active"
 },
 {
  "qualification_id": "Q:F-6-3",
  "parent_qualification_id": "Q:F-6",
  "manual_type": "both",
  "group": "F",
  "code": "F-6-3",
  "name_ko": "혼인단절자",
  "activity_scope": "",
  "eligible_persons": "",
  "stay_limit": "3년",
  "delegated_to": null,
  "program_ids": [],
  "sub_codes": [],
  "confidence": "medium",
  "notes": "명칭은 v2 업무명 유래  매뉴얼 매뉴얼 기준 명칭 대조 필요.",
  "status": "active"
 },
 {
  "qualification_id": "Q:G-1-10",
  "parent_qualification_id": "Q:G-1",
  "manual_type": "both",
  "group": "G",
  "code": "G-1-10",
  "name_ko": "외국인환자",
  "activity_scope": "",
  "eligible_persons": "",
  "stay_limit": "1년",
  "delegated_to": null,
  "program_ids": [],
  "sub_codes": [],
  "confidence": "medium",
  "notes": "route 소유 주체로 자동 생성  매뉴얼 매뉴얼 기준 명칭 대조 필요.",
  "status": "active"
 },
 {
  "qualification_id": "Q:F-3-19",
  "parent_qualification_id": "Q:F-3",
  "manual_type": "both",
  "group": "F",
  "code": "F-3-19",
  "name_ko": "재외동포(F-4) 가족 동반",
  "activity_scope": "",
  "eligible_persons": "재외동포(F-4) 자격자의 배우자 및 미성년 자녀(혼인한 자녀 제외, 미성년 자녀는 25세까지 체류허가)",
  "stay_limit": "",
  "delegated_to": null,
  "program_ids": [],
  "sub_codes": [],
  "confidence": "high",
  "notes": "[260709 신규 등재] 구 F-1-9(재외동포 가족 방문동거)를 대체하는 현행 코드 — 체류 변경허가(체류매뉴얼 p425), 사증은 1년 유효 복수(체류 1년, 사증매뉴얼 p318). 원문 표기는 '동반(F-3-19)'과 '방문동거(F-3-19)'가 혼재하나 코드·대상은 일관(F-3 계열 명칭 채택).",
  "status": "active"
 },
 {
  "qualification_id": "Q:F-3-20",
  "parent_qualification_id": "Q:F-3",
  "manual_type": "both",
  "group": "F",
  "code": "F-3-20",
  "name_ko": "방문취업(H-2) 가족 동반",
  "activity_scope": "",
  "eligible_persons": "방문취업(H-2) 자격자의 배우자 및 미성년 자녀(H-2 자격자의 체류기간까지 체류허가)",
  "stay_limit": "",
  "delegated_to": null,
  "program_ids": [],
  "sub_codes": [],
  "confidence": "high",
  "notes": "[260709 신규 등재] 구 F-1-11(방문취업자 가족 방문동거)을 대체하는 현행 코드 — 체류 변경허가(체류매뉴얼 p425), 사증은 1년 유효 복수(체류 90일, 사증매뉴얼 p318).",
  "status": "active"
 },
 {
  "qualification_id": "Q:F-1-D",
  "parent_qualification_id": "Q:F-1",
  "manual_type": "both",
  "group": "F",
  "code": "F-1-D",
  "name_ko": "디지털노마드(워케이션)",
  "activity_scope": "",
  "eligible_persons": "해외 사업체 소유자 또는 해외 기업 소속으로 원격근무가 가능한 사람 중 동일 업종 1년 이상 근무자 및 그 가족(본인 18세 이상)",
  "stay_limit": "1년(연장은 1회 1년, 최장 3년)",
  "delegated_to": null,
  "program_ids": [],
  "sub_codes": [],
  "confidence": "high",
  "notes": "[260709 신규 등재] 소득요건: 전년도 1인당 GNI 기준 연령(18~34세 1.5배/35세 이상 2배)·체류지역(비수도권·인구감소지역 완화)별 차등, 가족 동반 시 예외 적용. 의료보험 보장액 1억원 이상 가입 필요. 변경허가(체류 p349~350)·연장(체류 p358, 소득요건 완화자는 실체류 확인·수도권 이동 시 6개월 조건부)·사증(복수 1년, 사증 p305~306). 문자 세부코드(D)는 정렬·코드검증 정규식에서 기존 지원 확인(E-7-S1·F-2-7S 선례).",
  "status": "active"
 },
 {
  "qualification_id": "Q:F-1-12",
  "parent_qualification_id": "Q:F-1",
  "manual_type": "stay",
  "group": "F",
  "code": "F-1-12",
  "name_ko": "점수제 우수인재 가족 방문동거",
  "activity_scope": "방문동거. 취업은 원칙적으로 불가(관서장 판단 시 제한적 허용).",
  "eligible_persons": "점수제 우수인재(F-2-7/F-2-7S)의 배우자 등 가족 및 국내 출생 미성년 자녀. 주 자격자 연간소득이 1인당 국민소득 미만인 경우 F-2-71 대신 부여.",
  "stay_limit": "주 자격자의 체류기간에 따름",
  "delegated_to": null,
  "program_ids": [],
  "sub_codes": [],
  "confidence": "high",
  "notes": "점수제 우수인재 가족 방문동거(F-1-12). 주 자격자 합법체류 및 소득요건(GNI 미충족 시 F-2-71 대신 부여). F-2-7S는 초청자 자격변경일부터 5년간 국내 출생 자녀 F-2-71, 5년 경과 후 소득 미충족 시 F-1-12. 근거 체류 p342·p353.",
  "status": "active"
 },
 {
  "qualification_id": "Q:F-1-13",
  "parent_qualification_id": "Q:F-1",
  "manual_type": "both",
  "group": "F",
  "code": "F-1-13",
  "name_ko": "외국인유학생(고교 이하) 동반부모",
  "activity_scope": "유학생 동반 방문동거. 취업 불가.",
  "eligible_persons": "고등학교 이하 교육기관 유학(D-4-3) 외국인유학생의 동반 부모(2촌 이내 친인척, 재정요건 충족)",
  "stay_limit": "동반 외국인유학생의 체류기간에 따름",
  "delegated_to": null,
  "program_ids": [],
  "sub_codes": [],
  "confidence": "high",
  "notes": "외국인유학생(고교 이하) 동반부모(F-1-13). 자격변경(체류 p345)·외국인등록(체류 p359)·공관장 재량 사증(사증 p299) 성립. ",
  "status": "active"
 },
 {
  "qualification_id": "Q:F-1-28",
  "parent_qualification_id": "Q:F-1",
  "manual_type": "stay",
  "group": "F",
  "code": "F-1-28",
  "name_ko": "귀화자의 외국국적 부모 등",
  "activity_scope": "방문동거(결혼이민자 부모 등 가족 F-1-5 준용).",
  "eligible_persons": "귀화자의 외국국적 부모 등 — 체류허가 기준은 결혼이민자의 부모 등 가족(F-1-5) 준용",
  "stay_limit": "2년(결혼이민자 부모 등 가족 F-1-5 준용)",
  "delegated_to": null,
  "program_ids": [],
  "sub_codes": [],
  "confidence": "high",
  "notes": "귀화자의 외국국적 부모 등(F-1-28). 체류허가 기준은 「자녀양육 지원 등 목적으로 입국한 결혼이민자의 부모 등 가족(F-1-5)」 준용(체류 p347·p353). 260709 사증매뉴얼 미기재로 별도 사증경로 없음(F-1-5 준용).",
  "status": "active"
 },
 {
  "qualification_id": "Q:F-2-T1",
  "parent_qualification_id": "Q:F-2",
  "manual_type": "both",
  "group": "F",
  "code": "F-2-T1",
  "name_ko": "탑티어 동반 거주",
  "activity_scope": "종사 직종과 관계없이 취업활동 제한을 받지 않음(취업제한분야 제외, 출입국관리법 시행령 제23조 제2항).",
  "eligible_persons": "탑티어 거주(F-2-T) 자격자의 배우자 및 미성년 자녀(국내 출생 자녀 포함)",
  "stay_limit": "주 자격자와 동일",
  "delegated_to": null,
  "program_ids": [
   "PG:TOP_TIER"
  ],
  "sub_codes": [],
  "confidence": "high",
  "notes": "탑티어 동반 거주(F-2-T1). 심사: 체류허가 제한 대상 해당 여부, 혼인의 진정성·혼인 성립, 주 자격자의 톱티어 거주(F-2-T) 사증발급 요건 충족 여부. 근거 체류 p687·p688.",
  "status": "active"
 },
 {
  "qualification_id": "Q:F-5-T1",
  "parent_qualification_id": "Q:F-5",
  "manual_type": "both",
  "group": "F",
  "code": "F-5-T1",
  "name_ko": "탑티어 동반 영주",
  "activity_scope": "영주자격으로 취업 등 활동 제한이 없음.",
  "eligible_persons": "탑티어 동반 거주(F-2-T1)로 3년 이상 체류한 사람, 또는 탑티어가 영주(F-5-T) 취득 후 동반가족으로 입국하여 F-2-T1으로 2년 이상 체류한 사람",
  "stay_limit": "상한 없음",
  "delegated_to": null,
  "program_ids": [
   "PG:TOP_TIER"
  ],
  "sub_codes": [],
  "confidence": "high",
  "notes": "탑티어 동반 영주(F-5-T1). 심사: 체류허가 제한 대상 해당 여부, 품행 단정 및 법무부장관이 정하는 요건 종합심사. 근거 체류 p689·p690.",
  "status": "active"
 },
 {
  "qualification_id": "Q:F-3-17",
  "parent_qualification_id": "Q:F-3",
  "manual_type": "both",
  "group": "F",
  "code": "F-3-17",
  "name_ko": "유망탑티어(E-7) 동반가족",
  "activity_scope": "주 자격자의 체류자격에 상응하는 동반가족 활동.",
  "eligible_persons": "유망탑티어 특정활동(E-7-T) 자격자의 배우자 및 미성년 자녀",
  "stay_limit": "주 자격자와 동일",
  "delegated_to": null,
  "program_ids": [
   "PG:TOP_TIER"
  ],
  "sub_codes": [],
  "confidence": "medium",
  "notes": "유망탑티어(E-7-T) 동반가족(배우자·미성년자녀). 대상별 세부약호표 근거(체류 p687). 동반가족 공통 심사·제출서류 적용.",
  "status": "active"
 },
 {
  "qualification_id": "Q:F-3-10",
  "parent_qualification_id": "Q:F-3",
  "manual_type": "both",
  "group": "F",
  "code": "F-3-10",
  "name_ko": "예비탑티어(D-10) 동반가족",
  "activity_scope": "주 자격자의 체류자격에 상응하는 동반가족 활동.",
  "eligible_persons": "예비탑티어 구직(D-10-T) 자격자의 배우자 및 미성년 자녀",
  "stay_limit": "주 자격자와 동일",
  "delegated_to": null,
  "program_ids": [
   "PG:TOP_TIER"
  ],
  "sub_codes": [],
  "confidence": "medium",
  "notes": "예비탑티어(D-10-T) 동반가족(배우자·미성년자녀). 대상별 세부약호표 근거(체류 p687). 동반가족 공통 심사·제출서류 적용.",
  "status": "active"
 },
 {
  "qualification_id": "Q:F-5-6R",
  "parent_qualification_id": "Q:F-5",
  "manual_type": "both",
  "group": "F",
  "code": "F-5-6R",
  "name_ko": "지역특화형 재외동포영주",
  "activity_scope": "영주자격으로 취업 등 활동에 원칙적 제한이 없음(일부 직종 취업 제한 있음). 인구감소지역 지역특화 정착 목적.",
  "eligible_persons": "지역특화동포(F-4-R)로 자격변경 후 추천지역에 4년 이상(기존거주자 요건으로 변경한 사람은 2년) 계속 거주하며 자격을 유지한 외국국적동포",
  "stay_limit": "상한 없음",
  "delegated_to": null,
  "program_ids": [
   "PG:REGIONAL"
  ],
  "sub_codes": [],
  "confidence": "high",
  "notes": "지역특화형 재외동포영주(지역동포영주). 요건: 품행 단정(외국국적동포 업무처리지침), 생계유지능력(소득 1인당 GNI의 70%로 완화), 기본소양(사회통합프로그램 5단계 이상 이수 등). 근거 체류 p623·p624.",
  "status": "active"
 },
 {
  "qualification_id": "Q:D-8-4",
  "parent_qualification_id": "Q:D-8",
  "manual_type": "both",
  "group": "D",
  "code": "D-8-4",
  "name_ko": "기술창업",
  "activity_scope": "법인 경영·기술 분야 활동. 자격외활동은 본인의 벤처투자·기술창업 관련 활동만 허용.",
  "eligible_persons": "지식재산권 보유 등 우수한 기술력으로 국내 법인을 창업한 사람(점수제) 또는 K-Startup 그랜드챌린지 참여자·창업지원사업 수혜자·스타트업코리아 특별비자 추천자(점수제 면제)",
  "stay_limit": "2년",
  "delegated_to": null,
  "program_ids": [
   "PG:K_STAR"
  ],
  "sub_codes": [],
  "confidence": "high",
  "notes": "기술창업(D-8-4). 점수제 적용(전문학사 이상·60/300점·법인설립) 또는 점수제 면제(중기부 추천 등). 제출서류는 법인투자(D-8-1) 준용. 근거 체류 p115·p117·p118.",
  "status": "active"
 },
 {
  "qualification_id": "Q:D-8-4S",
  "parent_qualification_id": "Q:D-8",
  "manual_type": "both",
  "group": "D",
  "code": "D-8-4S",
  "name_ko": "기술창업-스타트업코리아 특별비자",
  "activity_scope": "기술창업(D-8-4)와 동일한 법인 경영·기술 분야 활동.",
  "eligible_persons": "스타트업코리아 특별비자 추천 민간평가위원회 심사승인 및 중소벤처기업부장관 추천을 받은 기술창업자(기술창업 점수제 면제 특례 유형)",
  "stay_limit": "2년",
  "delegated_to": null,
  "program_ids": [
   "PG:K_STAR"
  ],
  "sub_codes": [],
  "confidence": "medium",
  "notes": "기술창업-스타트업코리아 특별비자(D-8-4S). 기술창업(D-8-4)의 점수제 면제 특례 유형. 제출서류는 기술창업(D-8-4)/법인투자(D-8-1) 준용. 근거 체류 p115·p118.",
  "status": "active"
 },
 {
  "qualification_id": "Q:D-4-2K",
  "parent_qualification_id": "Q:D-4",
  "manual_type": "both",
  "group": "D",
  "code": "D-4-2K",
  "name_ko": "기업 맞춤형 인턴십(K-Trainee)",
  "activity_scope": "기업 맞춤형 인턴십(K-Trainee) 연수·인턴 활동. 인턴기간 원칙 6개월(추가 인정 시 입국일부터 1년 한도).",
  "eligible_persons": "기업 맞춤형 인턴십(K-Trainee) 프로그램 참여 외국인",
  "stay_limit": "2년(인턴기간 원칙 6개월, 최대 1년)",
  "delegated_to": null,
  "program_ids": [],
  "sub_codes": [],
  "confidence": "medium",
  "notes": "기업 맞춤형 인턴십 K-Trainee(D-4-2K). 전용 체류기간연장 제출서류. 근거 체류 p90·p91.",
  "status": "active"
 }
]
